slsdm-0.2.1.dist-info/RECORD
slsdm-0.2.1.dist-info/LICENSE
slsdm-0.2.1.dist-info/WHEEL
slsdm-0.2.1.dist-info/top_level.txt
slsdm-0.2.1.dist-info/METADATA
slsdm/_generate.py
slsdm/_dist_metrics.cpython-311-darwin.so
slsdm/__init__.py
slsdm/_dist_metrics.pxd
